setup.cfg
setup.py
craftbuildtools/__init__.py
craftbuildtools/__main__.py
craftbuildtools/app.py
craftbuildtools/bootstrap.py
craftbuildtools.egg-info/PKG-INFO
craftbuildtools.egg-info/SOURCES.txt
craftbuildtools.egg-info/dependency_links.txt
craftbuildtools.egg-info/entry_points.txt
craftbuildtools.egg-info/requires.txt
craftbuildtools.egg-info/top_level.txt
craftbuildtools/data/__init__.py
craftbuildtools/data/project.py
craftbuildtools/data/todo.py
craftbuildtools/operations/__init__.py
craftbuildtools/operations/addproject_operation.py
craftbuildtools/operations/build_operation.py
craftbuildtools/operations/clean_operation.py
craftbuildtools/operations/copy_operation.py
craftbuildtools/operations/createproject_operation.py
craftbuildtools/operations/downloadspigotbuildtools_operation.py
craftbuildtools/operations/editproject_operation.py
craftbuildtools/operations/listprojects_operation.py
craftbuildtools/operations/removeproject_operation.py
craftbuildtools/operations/todo_operation.py
craftbuildtools/operations/upload_operation.py
craftbuildtools/template/__init__.py
craftbuildtools/utils/__init__.py