Metadata-Version: 1.1
Name: craftbuildtools
Version: 0.1.6
Summary: Build automation and Project creation for Minecraft/Spigot/Bukkit, Maven Projects
Home-page: https://github.com/TechnicalBro/CraftBuildTools
Author: Brandon Curtis
Author-email: freebird.brandon@gmail.com
License: LICENSE.txt
Keywords: minecraft,spigot,bukkit,templates,buildtools,craftbuildtools
Platform: UNKNOWN
Classifier: Development Status :: 5 - Production/Stable
Classifier: Intended Audience :: Developers
Classifier: Intended Audience :: System Administrators
Classifier: Natural Language :: English
Classifier: License :: OSI Approved :: MIT License
Classifier: Programming Language :: Python
Classifier: Programming Language :: Python :: 3
Classifier: Programming Language :: Python :: 3.3
Classifier: Programming Language :: Python :: 3.4
